{
  "apiName": "api",
  "apiId": "",
  "deploymentName": "main",
  "environmentIds": [
    ""
  ],
  "api": {
    "enableGraphqlEndpoint": false,
    "operations": [
      {
        "content": "query AdminPortal {\n  searchAccount: portal_searchAccount {\n    companyId\n    products {\n      id\n      name\n      subscriptionIds\n      roles {\n        name\n        description\n        userCap\n      }\n    }\n    subscriptions {\n      id\n      application\n      status\n      cancelAt\n      cancelAtPeriodEnd\n      canceledAt\n      collectionMethod\n      created\n      createdByUserId\n      currentPeriodEnd\n      currentPeriodStart\n      daysUntilDueue\n      description\n      discount\n      endedAt\n      currency\n      type\n      items {\n        id\n        created\n        metadata {\n          name\n          type\n          value\n        }\n        price\n        quantity\n        subscription\n      }\n    }\n    users {\n      id\n      firstName\n      lastName\n      email\n      status\n      roles {\n        productId\n        roles\n      }\n    }\n    requests {\n      id\n      type\n      title\n      imageUrl\n      timestamp\n      cost\n      recurring\n      note\n      userId\n      statusId\n      statusTitle\n      typeId\n      typeTitle\n      productId\n      actions {\n        key\n        description\n        reasonNeeded\n      }\n    }\n    actionRequests {\n      requestId\n      action\n      reason\n    }\n    userInvitations {\n      email\n      phone\n      access {\n        productId\n        roles\n      }\n    }\n    payments {\n      id\n      amount\n      timestamp\n    }\n  }\n}",
        "name": "AdminPortal",
        "responseSchema": "{\"type\":\"object\",\"properties\":{\"data\":{\"type\":\"object\",\"properties\":{\"searchAccount\":{\"type\":\"array\",\"items\":{\"type\":\"object\",\"properties\":{\"companyId\":{\"type\":\"string\"},\"products\":{\"type\":\"array\",\"items\":{\"type\":\"object\",\"properties\":{\"id\":{\"type\":\"string\"},\"name\":{\"type\":\"string\"},\"subscriptionIds\":{\"type\":\"array\",\"items\":{\"type\":\"string\"}},\"roles\":{\"type\":\"array\",\"items\":{\"type\":\"object\",\"properties\":{\"name\":{\"type\":\"string\"},\"description\":{\"type\":\"string\"},\"userCap\":{\"type\":\"integer\"}},\"additionalProperties\":false,\"required\":[\"name\",\"description\",\"userCap\"]}}},\"additionalProperties\":false,\"required\":[\"id\",\"name\",\"roles\"]}},\"subscriptions\":{\"type\":\"array\",\"items\":{\"type\":\"object\",\"properties\":{\"id\":{\"type\":\"string\"},\"application\":{\"type\":\"string\"},\"status\":{\"type\":\"string\"},\"cancelAt\":{\"type\":\"string\"},\"cancelAtPeriodEnd\":{\"type\":\"boolean\"},\"canceledAt\":{\"type\":\"string\"},\"collectionMethod\":{\"type\":\"string\"},\"created\":{\"type\":\"string\"},\"createdByUserId\":{\"type\":\"string\"},\"currentPeriodEnd\":{\"type\":\"string\"},\"currentPeriodStart\":{\"type\":\"string\"},\"daysUntilDueue\":{\"type\":\"integer\"},\"description\":{\"type\":\"string\"},\"discount\":{\"type\":\"string\"},\"endedAt\":{\"type\":\"string\"},\"currency\":{\"type\":\"string\"},\"type\":{\"type\":\"string\"},\"items\":{\"type\":\"array\",\"items\":{\"type\":\"object\",\"properties\":{\"id\":{\"type\":\"string\"},\"created\":{\"type\":\"integer\"},\"metadata\":{\"type\":\"array\",\"items\":{\"type\":\"object\",\"properties\":{\"name\":{\"type\":\"string\"},\"type\":{\"type\":\"string\"},\"value\":{\"type\":\"string\"}},\"additionalProperties\":false}},\"price\":{},\"quantity\":{\"type\":\"integer\"},\"subscription\":{\"type\":\"string\"}},\"additionalProperties\":false,\"required\":[\"id\",\"created\",\"metadata\",\"price\",\"quantity\",\"subscription\"]}}},\"additionalProperties\":false,\"required\":[\"id\",\"application\",\"status\",\"cancelAt\",\"cancelAtPeriodEnd\",\"canceledAt\",\"collectionMethod\",\"created\",\"createdByUserId\",\"currentPeriodEnd\",\"currentPeriodStart\",\"daysUntilDueue\",\"description\",\"discount\",\"endedAt\",\"currency\",\"type\",\"items\"]}},\"users\":{\"type\":\"array\",\"items\":{\"type\":\"object\",\"properties\":{\"id\":{\"type\":\"string\"},\"firstName\":{\"type\":\"string\"},\"lastName\":{\"type\":\"string\"},\"email\":{\"type\":\"string\"},\"status\":{\"type\":\"string\"},\"roles\":{\"type\":\"array\",\"items\":{\"type\":\"object\",\"properties\":{\"productId\":{\"type\":\"string\"},\"roles\":{\"type\":\"array\",\"items\":{\"type\":\"string\"}}},\"additionalProperties\":false,\"required\":[\"productId\",\"roles\"]}}},\"additionalProperties\":false,\"required\":[\"id\",\"firstName\",\"lastName\",\"email\",\"status\",\"roles\"]}},\"requests\":{\"type\":\"array\",\"items\":{\"type\":\"object\",\"properties\":{\"id\":{\"type\":\"string\"},\"type\":{\"type\":\"string\"},\"title\":{\"type\":\"string\"},\"imageUrl\":{\"type\":\"string\"},\"timestamp\":{\"type\":\"string\"},\"cost\":{\"type\":\"string\"},\"recurring\":{\"type\":\"string\"},\"note\":{\"type\":\"string\"},\"userId\":{\"type\":\"string\"},\"statusId\":{\"type\":\"string\"},\"statusTitle\":{\"type\":\"string\"},\"typeId\":{\"type\":\"string\"},\"typeTitle\":{\"type\":\"string\"},\"productId\":{\"type\":\"string\"},\"actions\":{\"type\":\"array\",\"items\":{\"type\":\"object\",\"properties\":{\"key\":{\"type\":\"string\"},\"description\":{\"type\":\"string\"},\"reasonNeeded\":{\"type\":\"boolean\"}},\"additionalProperties\":false,\"required\":[\"key\",\"description\",\"reasonNeeded\"]}}},\"additionalProperties\":false,\"required\":[\"id\",\"type\",\"title\",\"imageUrl\",\"timestamp\",\"cost\",\"recurring\",\"note\",\"userId\",\"statusId\",\"statusTitle\",\"typeId\",\"typeTitle\",\"productId\",\"actions\"]}},\"actionRequests\":{\"type\":\"array\",\"items\":{\"type\":\"object\",\"properties\":{\"requestId\":{\"type\":\"string\"},\"action\":{\"type\":\"string\"},\"reason\":{\"type\":\"string\"}},\"additionalProperties\":false,\"required\":[\"action\"]}},\"userInvitations\":{\"type\":\"array\",\"items\":{\"type\":\"object\",\"properties\":{\"email\":{\"type\":\"string\"},\"phone\":{\"type\":\"string\"},\"access\":{\"type\":\"array\",\"items\":{\"type\":\"object\",\"properties\":{\"productId\":{\"type\":\"string\"},\"roles\":{\"type\":\"array\",\"items\":{\"type\":\"string\"}}},\"additionalProperties\":false,\"required\":[\"productId\",\"roles\"]}}},\"additionalProperties\":false,\"required\":[\"email\",\"phone\",\"access\"]}},\"payments\":{\"type\":\"array\",\"items\":{\"type\":\"object\",\"properties\":{\"id\":{\"type\":\"string\"},\"amount\":{\"type\":\"integer\"},\"timestamp\":{\"type\":\"string\"}},\"additionalProperties\":false,\"required\":[\"id\",\"amount\",\"timestamp\"]}}},\"additionalProperties\":false,\"required\":[\"companyId\",\"products\",\"subscriptions\",\"users\",\"requests\",\"actionRequests\",\"userInvitations\",\"payments\"]}}},\"additionalProperties\":false}},\"additionalProperties\":false}",
        "variablesSchema": "{\"type\":\"object\",\"properties\":{},\"additionalProperties\":false,\"definitions\":{}}",
        "interpolationVariablesSchema": "{\"type\":\"object\",\"properties\":{},\"additionalProperties\":false,\"definitions\":{}}",
        "operationType": 0,
        "cacheConfig": {
          "enable": false,
          "maxAge": 60,
          "public": true,
          "staleWhileRevalidate": 60
        },
        "authenticationConfig": {
          "authRequired": false
        },
        "authorizationConfig": {
          "claims": [],
          "roleConfig": {
            "requireMatchAll": [],
            "requireMatchAny": [],
            "denyMatchAll": [],
            "denyMatchAny": []
          }
        },
        "liveQueryConfig": {
          "enable": true,
          "pollingIntervalSeconds": 1
        },
        "hooksConfiguration": {
          "preResolve": false,
          "postResolve": false,
          "mutatingPreResolve": false,
          "mutatingPostResolve": false,
          "mockResolve": {
            "enable": false,
            "subscriptionPollingIntervalMillis": 0
          },
          "httpTransportOnResponse": false,
          "httpTransportOnRequest": false,
          "customResolve": false
        },
        "variablesConfiguration": {
          "injectVariables": []
        },
        "internal": false,
        "postResolveTransformations": []
      }
    ],
    "engineConfiguration": {
      "defaultFlushInterval": 500,
      "graphqlSchema": "directive @fromClaim(name: Claim) on VARIABLE_DEFINITION\n\ndirective @hooksVariable on VARIABLE_DEFINITION\n\ndirective @jsonSchema(\n  \"\"\"\n  The value of both of these keywords MUST be a string.\n  \n  Both of these keywords can be used to decorate a user interface with\n  information about the data produced by this user interface.  A title\n  will preferably be short, whereas a description will provide\n  explanation about the purpose of the instance described by this\n  schema.\n  \"\"\"\n  title: String\n  \"\"\"\n  The value of both of these keywords MUST be a string.\n  \n  Both of these keywords can be used to decorate a user interface with\n  information about the data produced by this user interface.  A title\n  will preferably be short, whereas a description will provide\n  explanation about the purpose of the instance described by this\n  schema.\n  \"\"\"\n  description: String\n  \"\"\"\n  The value of \"multipleOf\" MUST be a number, strictly greater than 0.\n  \n  A numeric instance is valid only if division by this keyword's value\n  results in an integer.\n  \"\"\"\n  multipleOf: Int\n  \"\"\"\n  The value of \"maximum\" MUST be a number, representing an inclusive\n  upper limit for a numeric instance.\n  \n  If the instance is a number, then this keyword validates only if the\n  instance is less than or exactly equal to \"maximum\".\n  \"\"\"\n  maximum: Int\n  \"\"\"\n  The value of \"exclusiveMaximum\" MUST be number, representing an\n  exclusive upper limit for a numeric instance.\n  \n  If the instance is a number, then the instance is valid only if it\n  has a value strictly less than (not equal to) \"exclusiveMaximum\".\n  \"\"\"\n  exclusiveMaximum: Int\n  \"\"\"\n  The value of \"minimum\" MUST be a number, representing an inclusive\n  lower limit for a numeric instance.\n  \n  If the instance is a number, then this keyword validates only if the\n  instance is greater than or exactly equal to \"minimum\".\n  \"\"\"\n  minimum: Int\n  \"\"\"\n  The value of \"exclusiveMinimum\" MUST be number, representing an\n  exclusive lower limit for a numeric instance.\n  \n  If the instance is a number, then the instance is valid only if it\n  has a value strictly greater than (not equal to) \"exclusiveMinimum\".\n  \"\"\"\n  exclusiveMinimum: Int\n  \"\"\"\n  The value of this keyword MUST be a non-negative integer.\n  \n  A string instance is valid against this keyword if its length is less\n  than, or equal to, the value of this keyword.\n  \n  The length of a string instance is defined as the number of its\n  characters as defined by RFC 7159 [RFC7159].\n  \"\"\"\n  maxLength: Int\n  \"\"\"\n  The value of this keyword MUST be a non-negative integer.\n  \n  A string instance is valid against this keyword if its length is\n  greater than, or equal to, the value of this keyword.\n  \n  The length of a string instance is defined as the number of its\n  characters as defined by RFC 7159 [RFC7159].\n  \n  Omitting this keyword has the same behavior as a value of 0.\n  \"\"\"\n  minLength: Int\n  \"\"\"\n  The value of this keyword MUST be a string.  This string SHOULD be a\n  valid regular expression, according to the ECMA 262 regular\n  expression dialect.\n  \n  A string instance is considered valid if the regular expression\n  matches the instance successfully.  Recall: regular expressions are\n  not implicitly anchored.\n  \"\"\"\n  pattern: String\n  \"\"\"\n  The value of this keyword MUST be a non-negative integer.\n  \n  An array instance is valid against \"maxItems\" if its size is less\n  than, or equal to, the value of this keyword.\n  \"\"\"\n  maxItems: Int\n  \"\"\"\n  The value of this keyword MUST be a non-negative integer.\n  \n  An array instance is valid against \"minItems\" if its size is greater\n  than, or equal to, the value of this keyword.\n  \n  Omitting this keyword has the same behavior as a value of 0.\n  \"\"\"\n  minItems: Int\n  \"\"\"\n  The value of this keyword MUST be a boolean.\n  \n  If this keyword has boolean value false, the instance validates\n  successfully.  If it has boolean value true, the instance validates\n  successfully if all of its elements are unique.\n  \n  Omitting this keyword has the same behavior as a value of false.\n  \"\"\"\n  uniqueItems: Boolean\n  commonPattern: COMMON_REGEX_PATTERN\n) on VARIABLE_DEFINITION\n\ndirective @rbac(\n  \"\"\"the user must match all roles\"\"\"\n  requireMatchAll: [WG_ROLE]\n  \"\"\"the user must match at least one of the roles\"\"\"\n  requireMatchAny: [WG_ROLE]\n  \"\"\"the user must not match all of the roles\"\"\"\n  denyMatchAll: [WG_ROLE]\n  \"\"\"the user must not match any of the roles\"\"\"\n  denyMatchAny: [WG_ROLE]\n) on QUERY | MUTATION | SUBSCRIPTION\n\n\"\"\"\nThe directive @injectCurrentDateTime injects a DateTime string of the current date and time into the variable.\nThis variable MUST be a string compatible scalar. \n\nThe default format, is: ISO 8601\nIf no format is chosen, the default format is used.\nCustom formats are allowed by specifying a format conforming to the Golang specification for specifying a date time format.\n\"\"\"\ndirective @injectCurrentDateTime(\n  format: WunderGraphDateTimeFormat = ISO8601\n  \"\"\"\n  customFormat must conform to the Golang specification for specifying a date time format\n  \"\"\"\n  customFormat: String\n) on VARIABLE_DEFINITION\n\n\"\"\"\nThe directive @injectGeneratedUUID injects a generated UUID into the variable.\nThis variable MUST be a string.\nAt the same time, it removes the variable from the input definition,\ndisallowing the user to supply it.\n\nThis means, the UUID is 100% generated server-side and can be considered untempered.\n\"\"\"\ndirective @injectGeneratedUUID on VARIABLE_DEFINITION\n\n\"\"\"\nThe @internalOperation Directive marks an Operation as internal.\nBy doing so, the Operation is no longer accessible from the public API.\nIt can only be accessed by internal services, like hooks.\n\"\"\"\ndirective @internalOperation on QUERY | MUTATION | SUBSCRIPTION\n\n\"\"\"\nThe directive @injectEnvironmentVariable allows you to inject an environment variable into the variable definition.\n\"\"\"\ndirective @injectEnvironmentVariable(name: String!) on VARIABLE_DEFINITION\n\n\"\"\"\nThe @export directive instructs the Execution Planner to export the field during the execution into the variable of the 'as' argument.\nAs the execution is depth first, a field can only be used after it has been exported.\nAdditionally, a field can only be used after using the '_join' field or on a different data source.\nIt's not possible to export a field and use it in for the same data source.\n\nNote that the @export directive only works on fields that return a single value.\nIt's not possible to export a list or object field.\n\"\"\"\ndirective @export(\n  \"\"\"The argument 'as' is the name of the variable to export the field to.\"\"\"\n  as: String!\n) on FIELD\n\n\"\"\"\nThe directive @internal marks a variable definition as internal so that clients can't access it.\nThe field is also not visible in the public API.\nIt's only being used as an internal variable to export fields into.\n\"\"\"\ndirective @internal on VARIABLE_DEFINITION\n\n\"\"\"\nThe @transform directive allows to apply transformations to the response.\nBy applying the directive, the shape of the response can be altered,\nwhich will also modify the JSON-Schema of the response.\nThat is, you will keep full type safety and code-generation for transformed fields.\n\"\"\"\ndirective @transform(\n  \"\"\"\n  Using the 'get' transformation allows you to extract a nested field using a JSON path.\n  This is useful to unnest data, e.g. when using the '_join' field, which adds an extra layer of nesting.\n  \n  Example:\n  \n  query GetName {\n      name: me @transform(get: \"info.name\") {\n          info {\n              name\n          }\n      }\n  }\n  \n  Before the transformation, the resolve looks like this:\n  \n  {\n      \"name\": {\n          \"info\": {\n              \"name\": \"John Doe\"\n          }\n      }\n  }\n  \n  With the transformation applied, the response will be reshaped like this:\n  \n  {\n      \"name\": \"John Doe\"\n  }\n  \"\"\"\n  get: String\n) on FIELD\n\ntype Query {\n  portal_searchAccount: [portal_portal]\n  portal_searchRequests: [portal_request]\n  gql_hello: String\n}\n\ntype Mutation {\n  portal_administer(postPortalInput: portal_administerCommandInput!): portal_ack\n}\n\ntype portal_portal {\n  companyId: String!\n  products: [portal_product]!\n  subscriptions: [portal_subscription]!\n  users: [portal_user]!\n  requests: [portal_request]!\n  actionRequests: [portal_actionRequest]!\n  userInvitations: [portal_userInvitation]!\n  payments: [portal_payment]!\n  _join: Query!\n}\n\ntype portal_product {\n  id: String!\n  name: String!\n  subscriptionIds: [String]\n  roles: [portal_productRole]!\n  _join: Query!\n}\n\ntype portal_productRole {\n  name: String!\n  description: String!\n  userCap: Int!\n  _join: Query!\n}\n\ntype portal_subscription {\n  id: String!\n  application: String!\n  status: String!\n  cancelAt: String!\n  cancelAtPeriodEnd: Boolean!\n  canceledAt: String!\n  collectionMethod: String!\n  created: String!\n  createdByUserId: String!\n  currentPeriodEnd: String!\n  currentPeriodStart: String!\n  daysUntilDueue: Int!\n  description: String!\n  discount: String!\n  endedAt: String!\n  currency: String!\n  type: String!\n  items: [portal_subscriptionItem]!\n  _join: Query!\n}\n\ntype portal_subscriptionItem {\n  id: String!\n  created: Int!\n  metadata: [portal_metadata]!\n  price: JSON!\n  quantity: Int!\n  subscription: String!\n  _join: Query!\n}\n\ntype portal_metadata {\n  name: String\n  type: String\n  value: String\n  _join: Query!\n}\n\nscalar JSON\n\ntype portal_user {\n  id: String!\n  firstName: String!\n  lastName: String!\n  email: String!\n  status: String!\n  roles: [portal_role]!\n  _join: Query!\n}\n\ntype portal_role {\n  productId: String!\n  roles: [String]!\n  _join: Query!\n}\n\ntype portal_request {\n  id: String!\n  type: String!\n  title: String!\n  imageUrl: String!\n  timestamp: String!\n  cost: String!\n  recurring: String!\n  note: String!\n  userId: String!\n  statusId: String!\n  statusTitle: String!\n  typeId: String!\n  typeTitle: String!\n  productId: String!\n  actions: [portal_requestAction]!\n  _join: Query!\n}\n\ntype portal_requestAction {\n  key: String!\n  description: String!\n  reasonNeeded: Boolean!\n  _join: Query!\n}\n\ntype portal_actionRequest {\n  requestId: String\n  action: String!\n  reason: String\n  _join: Query!\n}\n\ntype portal_userInvitation {\n  email: String!\n  phone: String!\n  access: [portal_role]!\n  _join: Query!\n}\n\ntype portal_payment {\n  id: String!\n  amount: Int!\n  timestamp: String!\n  _join: Query!\n}\n\ntype portal_ack {\n  success: Boolean\n  messages: [String]\n  _join: Query!\n}\n\ninput portal_administerCommandInput {\n  addUser: [portal_userInput]\n  userActions: [portal_userActionCommandInput]\n}\n\ninput portal_userInput {\n  id: String!\n  firstName: String!\n  lastName: String!\n  email: String!\n  status: String!\n  roles: [portal_roleInput]!\n}\n\ninput portal_roleInput {\n  productId: String!\n  roles: [String]!\n}\n\ninput portal_userActionCommandInput {\n  userId: String\n  actions: [String]\n}\n\nenum Claim {\n  EMAIL\n  EMAIL_VERIFIED\n  NAME\n  NICKNAME\n  LOCATION\n  PROVIDER\n}\n\nenum COMMON_REGEX_PATTERN {\n  EMAIL\n  DOMAIN\n}\n\nenum WG_ROLE {\n  admin\n  user\n}\n\nenum WunderGraphDateTimeFormat {\n  \"\"\"2006-01-02T15:04:05-0700\"\"\"\n  ISO8601\n  \"\"\"Mon Jan _2 15:04:05 2006\"\"\"\n  ANSIC\n  \"\"\"Mon Jan _2 15:04:05 MST 2006\"\"\"\n  UnixDate\n  \"\"\"Mon Jan 02 15:04:05 -0700 2006\"\"\"\n  RubyDate\n  \"\"\"02 Jan 06 15:04 MST\"\"\"\n  RFC822\n  \"\"\"02 Jan 06 15:04 -0700\"\"\"\n  RFC822Z\n  \"\"\"Monday, 02-Jan-06 15:04:05 MST\"\"\"\n  RFC850\n  \"\"\"Mon, 02 Jan 2006 15:04:05 MST\"\"\"\n  RFC1123\n  \"\"\"Mon, 02 Jan 2006 15:04:05 -0700\"\"\"\n  RFC1123Z\n  \"\"\"2006-01-02T15:04:05Z07:00\"\"\"\n  RFC3339\n  \"\"\"2006-01-02T15:04:05.999999999Z07:00\"\"\"\n  RFC3339Nano\n  \"\"\"3:04PM\"\"\"\n  Kitchen\n  \"\"\"Jan _2 15:04:05\"\"\"\n  Stamp\n  \"\"\"Jan _2 15:04:05.000\"\"\"\n  StampMilli\n  \"\"\"Jan _2 15:04:05.000000\"\"\"\n  StampMicro\n  \"\"\"Jan _2 15:04:05.000000000\"\"\"\n  StampNano\n}",
      "datasourceConfigurations": [
        {
          "kind": 1,
          "rootNodes": [
            {
              "typeName": "Query",
              "fieldNames": [
                "portal_searchAccount"
              ]
            }
          ],
          "childNodes": [],
          "customRest": {
            "fetch": {
              "method": 0,
              "url": {
                "kind": 0,
                "environmentVariableDefaultValue": "",
                "environmentVariableName": "",
                "placeholderVariableName": "",
                "staticVariableContent": "https://localhost:7254/TruthShield/customer-portal/1.0.0/portal"
              },
              "body": {
                "kind": 0,
                "environmentVariableDefaultValue": "",
                "environmentVariableName": "",
                "placeholderVariableName": "",
                "staticVariableContent": ""
              },
              "header": {
                "AuthToken": {
                  "values": [
                    {
                      "kind": 0,
                      "staticVariableContent": "staticToken",
                      "environmentVariableDefaultValue": "",
                      "environmentVariableName": "",
                      "placeholderVariableName": ""
                    }
                  ]
                },
                "Authorization": {
                  "values": [
                    {
                      "kind": 0,
                      "staticVariableContent": "{{ .request.headers.Authorization }}",
                      "environmentVariableName": "",
                      "environmentVariableDefaultValue": "",
                      "placeholderVariableName": ""
                    }
                  ]
                }
              },
              "query": [],
              "urlEncodeBody": false
            },
            "subscription": {
              "enabled": false,
              "pollingIntervalMillis": 500,
              "skipPublishSameResponse": false
            },
            "defaultTypeName": "",
            "statusCodeTypeMappings": []
          },
          "overrideFieldPathFromAlias": false,
          "directives": []
        },
        {
          "kind": 1,
          "rootNodes": [
            {
              "typeName": "Mutation",
              "fieldNames": [
                "portal_administer"
              ]
            }
          ],
          "childNodes": [],
          "customRest": {
            "fetch": {
              "method": 1,
              "url": {
                "kind": 0,
                "environmentVariableDefaultValue": "",
                "environmentVariableName": "",
                "placeholderVariableName": "",
                "staticVariableContent": "https://localhost:7254/TruthShield/customer-portal/1.0.0/portal"
              },
              "body": {
                "kind": 0,
                "staticVariableContent": "{{ .arguments.postPortalInput }}",
                "environmentVariableName": "",
                "environmentVariableDefaultValue": "",
                "placeholderVariableName": ""
              },
              "header": {
                "AuthToken": {
                  "values": [
                    {
                      "kind": 0,
                      "staticVariableContent": "staticToken",
                      "environmentVariableDefaultValue": "",
                      "environmentVariableName": "",
                      "placeholderVariableName": ""
                    }
                  ]
                },
                "Authorization": {
                  "values": [
                    {
                      "kind": 0,
                      "staticVariableContent": "{{ .request.headers.Authorization }}",
                      "environmentVariableName": "",
                      "environmentVariableDefaultValue": "",
                      "placeholderVariableName": ""
                    }
                  ]
                }
              },
              "query": [],
              "urlEncodeBody": false
            },
            "subscription": {
              "enabled": false,
              "pollingIntervalMillis": 500,
              "skipPublishSameResponse": false
            },
            "defaultTypeName": "",
            "statusCodeTypeMappings": []
          },
          "overrideFieldPathFromAlias": false,
          "directives": []
        },
        {
          "kind": 1,
          "rootNodes": [
            {
              "typeName": "Query",
              "fieldNames": [
                "portal_searchRequests"
              ]
            }
          ],
          "childNodes": [],
          "customRest": {
            "fetch": {
              "method": 0,
              "url": {
                "kind": 0,
                "environmentVariableDefaultValue": "",
                "environmentVariableName": "",
                "placeholderVariableName": "",
                "staticVariableContent": "https://localhost:7254/TruthShield/customer-portal/1.0.0/admin-requests"
              },
              "body": {
                "kind": 0,
                "environmentVariableDefaultValue": "",
                "environmentVariableName": "",
                "placeholderVariableName": "",
                "staticVariableContent": ""
              },
              "header": {
                "AuthToken": {
                  "values": [
                    {
                      "kind": 0,
                      "staticVariableContent": "staticToken",
                      "environmentVariableDefaultValue": "",
                      "environmentVariableName": "",
                      "placeholderVariableName": ""
                    }
                  ]
                },
                "Authorization": {
                  "values": [
                    {
                      "kind": 0,
                      "staticVariableContent": "{{ .request.headers.Authorization }}",
                      "environmentVariableName": "",
                      "environmentVariableDefaultValue": "",
                      "placeholderVariableName": ""
                    }
                  ]
                }
              },
              "query": [],
              "urlEncodeBody": false
            },
            "subscription": {
              "enabled": false,
              "pollingIntervalMillis": 500,
              "skipPublishSameResponse": false
            },
            "defaultTypeName": "",
            "statusCodeTypeMappings": []
          },
          "overrideFieldPathFromAlias": false,
          "directives": []
        },
        {
          "kind": 2,
          "customGraphql": {
            "fetch": {
              "url": {
                "kind": 0,
                "environmentVariableDefaultValue": "",
                "environmentVariableName": "",
                "placeholderVariableName": "",
                "staticVariableContent": "http://127.0.0.1:9992/gqls/gql/graphql"
              },
              "method": 1,
              "body": {
                "kind": 0,
                "environmentVariableDefaultValue": "",
                "environmentVariableName": "",
                "placeholderVariableName": "",
                "staticVariableContent": ""
              },
              "header": {
                "X-WG-Internal-GraphQL-API": {
                  "values": [
                    {
                      "kind": 0,
                      "staticVariableContent": "true",
                      "environmentVariableName": "",
                      "environmentVariableDefaultValue": "",
                      "placeholderVariableName": ""
                    }
                  ]
                }
              },
              "query": [],
              "urlEncodeBody": false
            },
            "federation": {
              "enabled": false,
              "serviceSdl": ""
            },
            "subscription": {
              "enabled": false,
              "url": {
                "kind": 0,
                "environmentVariableDefaultValue": "",
                "environmentVariableName": "",
                "placeholderVariableName": "",
                "staticVariableContent": "ws://127.0.0.1:9992/gqls/gql/graphql"
              }
            },
            "upstreamSchema": "schema {\n  query: Query\n}\n\ntype Query {\n  hello: String\n}"
          },
          "rootNodes": [
            {
              "typeName": "Query",
              "fieldNames": [
                "gql_hello"
              ]
            }
          ],
          "childNodes": [],
          "overrideFieldPathFromAlias": true,
          "directives": []
        },
        {
          "kind": 0,
          "rootNodes": [
            {
              "typeName": "portal_portal",
              "fieldNames": [
                "_join"
              ]
            }
          ],
          "childNodes": [],
          "customStatic": {
            "data": {
              "kind": 0,
              "staticVariableContent": "{}",
              "placeholderVariableName": "",
              "environmentVariableDefaultValue": "",
              "environmentVariableName": ""
            }
          },
          "overrideFieldPathFromAlias": false,
          "directives": []
        },
        {
          "kind": 0,
          "rootNodes": [
            {
              "typeName": "portal_product",
              "fieldNames": [
                "_join"
              ]
            }
          ],
          "childNodes": [],
          "customStatic": {
            "data": {
              "kind": 0,
              "staticVariableContent": "{}",
              "placeholderVariableName": "",
              "environmentVariableDefaultValue": "",
              "environmentVariableName": ""
            }
          },
          "overrideFieldPathFromAlias": false,
          "directives": []
        },
        {
          "kind": 0,
          "rootNodes": [
            {
              "typeName": "portal_productRole",
              "fieldNames": [
                "_join"
              ]
            }
          ],
          "childNodes": [],
          "customStatic": {
            "data": {
              "kind": 0,
              "staticVariableContent": "{}",
              "placeholderVariableName": "",
              "environmentVariableDefaultValue": "",
              "environmentVariableName": ""
            }
          },
          "overrideFieldPathFromAlias": false,
          "directives": []
        },
        {
          "kind": 0,
          "rootNodes": [
            {
              "typeName": "portal_subscription",
              "fieldNames": [
                "_join"
              ]
            }
          ],
          "childNodes": [],
          "customStatic": {
            "data": {
              "kind": 0,
              "staticVariableContent": "{}",
              "placeholderVariableName": "",
              "environmentVariableDefaultValue": "",
              "environmentVariableName": ""
            }
          },
          "overrideFieldPathFromAlias": false,
          "directives": []
        },
        {
          "kind": 0,
          "rootNodes": [
            {
              "typeName": "portal_subscriptionItem",
              "fieldNames": [
                "_join"
              ]
            }
          ],
          "childNodes": [],
          "customStatic": {
            "data": {
              "kind": 0,
              "staticVariableContent": "{}",
              "placeholderVariableName": "",
              "environmentVariableDefaultValue": "",
              "environmentVariableName": ""
            }
          },
          "overrideFieldPathFromAlias": false,
          "directives": []
        },
        {
          "kind": 0,
          "rootNodes": [
            {
              "typeName": "portal_metadata",
              "fieldNames": [
                "_join"
              ]
            }
          ],
          "childNodes": [],
          "customStatic": {
            "data": {
              "kind": 0,
              "staticVariableContent": "{}",
              "placeholderVariableName": "",
              "environmentVariableDefaultValue": "",
              "environmentVariableName": ""
            }
          },
          "overrideFieldPathFromAlias": false,
          "directives": []
        },
        {
          "kind": 0,
          "rootNodes": [
            {
              "typeName": "portal_user",
              "fieldNames": [
                "_join"
              ]
            }
          ],
          "childNodes": [],
          "customStatic": {
            "data": {
              "kind": 0,
              "staticVariableContent": "{}",
              "placeholderVariableName": "",
              "environmentVariableDefaultValue": "",
              "environmentVariableName": ""
            }
          },
          "overrideFieldPathFromAlias": false,
          "directives": []
        },
        {
          "kind": 0,
          "rootNodes": [
            {
              "typeName": "portal_role",
              "fieldNames": [
                "_join"
              ]
            }
          ],
          "childNodes": [],
          "customStatic": {
            "data": {
              "kind": 0,
              "staticVariableContent": "{}",
              "placeholderVariableName": "",
              "environmentVariableDefaultValue": "",
              "environmentVariableName": ""
            }
          },
          "overrideFieldPathFromAlias": false,
          "directives": []
        },
        {
          "kind": 0,
          "rootNodes": [
            {
              "typeName": "portal_request",
              "fieldNames": [
                "_join"
              ]
            }
          ],
          "childNodes": [],
          "customStatic": {
            "data": {
              "kind": 0,
              "staticVariableContent": "{}",
              "placeholderVariableName": "",
              "environmentVariableDefaultValue": "",
              "environmentVariableName": ""
            }
          },
          "overrideFieldPathFromAlias": false,
          "directives": []
        },
        {
          "kind": 0,
          "rootNodes": [
            {
              "typeName": "portal_requestAction",
              "fieldNames": [
                "_join"
              ]
            }
          ],
          "childNodes": [],
          "customStatic": {
            "data": {
              "kind": 0,
              "staticVariableContent": "{}",
              "placeholderVariableName": "",
              "environmentVariableDefaultValue": "",
              "environmentVariableName": ""
            }
          },
          "overrideFieldPathFromAlias": false,
          "directives": []
        },
        {
          "kind": 0,
          "rootNodes": [
            {
              "typeName": "portal_actionRequest",
              "fieldNames": [
                "_join"
              ]
            }
          ],
          "childNodes": [],
          "customStatic": {
            "data": {
              "kind": 0,
              "staticVariableContent": "{}",
              "placeholderVariableName": "",
              "environmentVariableDefaultValue": "",
              "environmentVariableName": ""
            }
          },
          "overrideFieldPathFromAlias": false,
          "directives": []
        },
        {
          "kind": 0,
          "rootNodes": [
            {
              "typeName": "portal_userInvitation",
              "fieldNames": [
                "_join"
              ]
            }
          ],
          "childNodes": [],
          "customStatic": {
            "data": {
              "kind": 0,
              "staticVariableContent": "{}",
              "placeholderVariableName": "",
              "environmentVariableDefaultValue": "",
              "environmentVariableName": ""
            }
          },
          "overrideFieldPathFromAlias": false,
          "directives": []
        },
        {
          "kind": 0,
          "rootNodes": [
            {
              "typeName": "portal_payment",
              "fieldNames": [
                "_join"
              ]
            }
          ],
          "childNodes": [],
          "customStatic": {
            "data": {
              "kind": 0,
              "staticVariableContent": "{}",
              "placeholderVariableName": "",
              "environmentVariableDefaultValue": "",
              "environmentVariableName": ""
            }
          },
          "overrideFieldPathFromAlias": false,
          "directives": []
        },
        {
          "kind": 0,
          "rootNodes": [
            {
              "typeName": "portal_ack",
              "fieldNames": [
                "_join"
              ]
            }
          ],
          "childNodes": [],
          "customStatic": {
            "data": {
              "kind": 0,
              "staticVariableContent": "{}",
              "placeholderVariableName": "",
              "environmentVariableDefaultValue": "",
              "environmentVariableName": ""
            }
          },
          "overrideFieldPathFromAlias": false,
          "directives": []
        }
      ],
      "fieldConfigurations": [
        {
          "typeName": "Query",
          "fieldName": "portal_searchAccount",
          "disableDefaultFieldMapping": true,
          "argumentsConfiguration": [],
          "requiresFields": [],
          "path": [],
          "unescapeResponseJson": false
        },
        {
          "typeName": "Mutation",
          "fieldName": "portal_administer",
          "disableDefaultFieldMapping": true,
          "argumentsConfiguration": [],
          "requiresFields": [],
          "path": [],
          "unescapeResponseJson": false
        },
        {
          "typeName": "Query",
          "fieldName": "portal_searchRequests",
          "disableDefaultFieldMapping": true,
          "argumentsConfiguration": [],
          "requiresFields": [],
          "path": [],
          "unescapeResponseJson": false
        },
        {
          "typeName": "Query",
          "fieldName": "gql_hello",
          "disableDefaultFieldMapping": false,
          "path": [
            "hello"
          ],
          "argumentsConfiguration": [],
          "requiresFields": [],
          "unescapeResponseJson": false
        },
        {
          "typeName": "portal_portal",
          "fieldName": "_join",
          "disableDefaultFieldMapping": true,
          "path": [
            "_join"
          ],
          "requiresFields": [],
          "argumentsConfiguration": [],
          "unescapeResponseJson": false
        },
        {
          "typeName": "portal_product",
          "fieldName": "_join",
          "disableDefaultFieldMapping": true,
          "path": [
            "_join"
          ],
          "requiresFields": [],
          "argumentsConfiguration": [],
          "unescapeResponseJson": false
        },
        {
          "typeName": "portal_productRole",
          "fieldName": "_join",
          "disableDefaultFieldMapping": true,
          "path": [
            "_join"
          ],
          "requiresFields": [],
          "argumentsConfiguration": [],
          "unescapeResponseJson": false
        },
        {
          "typeName": "portal_subscription",
          "fieldName": "_join",
          "disableDefaultFieldMapping": true,
          "path": [
            "_join"
          ],
          "requiresFields": [],
          "argumentsConfiguration": [],
          "unescapeResponseJson": false
        },
        {
          "typeName": "portal_subscriptionItem",
          "fieldName": "_join",
          "disableDefaultFieldMapping": true,
          "path": [
            "_join"
          ],
          "requiresFields": [],
          "argumentsConfiguration": [],
          "unescapeResponseJson": false
        },
        {
          "typeName": "portal_metadata",
          "fieldName": "_join",
          "disableDefaultFieldMapping": true,
          "path": [
            "_join"
          ],
          "requiresFields": [],
          "argumentsConfiguration": [],
          "unescapeResponseJson": false
        },
        {
          "typeName": "portal_user",
          "fieldName": "_join",
          "disableDefaultFieldMapping": true,
          "path": [
            "_join"
          ],
          "requiresFields": [],
          "argumentsConfiguration": [],
          "unescapeResponseJson": false
        },
        {
          "typeName": "portal_role",
          "fieldName": "_join",
          "disableDefaultFieldMapping": true,
          "path": [
            "_join"
          ],
          "requiresFields": [],
          "argumentsConfiguration": [],
          "unescapeResponseJson": false
        },
        {
          "typeName": "portal_request",
          "fieldName": "_join",
          "disableDefaultFieldMapping": true,
          "path": [
            "_join"
          ],
          "requiresFields": [],
          "argumentsConfiguration": [],
          "unescapeResponseJson": false
        },
        {
          "typeName": "portal_requestAction",
          "fieldName": "_join",
          "disableDefaultFieldMapping": true,
          "path": [
            "_join"
          ],
          "requiresFields": [],
          "argumentsConfiguration": [],
          "unescapeResponseJson": false
        },
        {
          "typeName": "portal_actionRequest",
          "fieldName": "_join",
          "disableDefaultFieldMapping": true,
          "path": [
            "_join"
          ],
          "requiresFields": [],
          "argumentsConfiguration": [],
          "unescapeResponseJson": false
        },
        {
          "typeName": "portal_userInvitation",
          "fieldName": "_join",
          "disableDefaultFieldMapping": true,
          "path": [
            "_join"
          ],
          "requiresFields": [],
          "argumentsConfiguration": [],
          "unescapeResponseJson": false
        },
        {
          "typeName": "portal_payment",
          "fieldName": "_join",
          "disableDefaultFieldMapping": true,
          "path": [
            "_join"
          ],
          "requiresFields": [],
          "argumentsConfiguration": [],
          "unescapeResponseJson": false
        },
        {
          "typeName": "portal_ack",
          "fieldName": "_join",
          "disableDefaultFieldMapping": true,
          "path": [
            "_join"
          ],
          "requiresFields": [],
          "argumentsConfiguration": [],
          "unescapeResponseJson": false
        }
      ],
      "typeConfigurations": []
    },
    "s3UploadConfiguration": [],
    "corsConfiguration": {
      "maxAge": 120,
      "allowedHeaders": [
        "*"
      ],
      "allowedMethods": [
        "GET",
        "POST"
      ],
      "exposedHeaders": [
        "*"
      ],
      "allowCredentials": true,
      "allowedOrigins": [
        {
          "kind": 0,
          "environmentVariableDefaultValue": "",
          "environmentVariableName": "",
          "placeholderVariableName": "",
          "staticVariableContent": "http://localhost:3000"
        }
      ]
    },
    "authenticationConfig": {
      "cookieBased": {
        "providers": [
          {
            "kind": 0,
            "githubConfig": {
              "clientId": {
                "kind": 0,
                "environmentVariableDefaultValue": "",
                "environmentVariableName": "",
                "placeholderVariableName": "",
                "staticVariableContent": "demo"
              },
              "clientSecret": {
                "kind": 0,
                "environmentVariableDefaultValue": "",
                "environmentVariableName": "",
                "placeholderVariableName": "",
                "staticVariableContent": "demo"
              }
            },
            "id": "github"
          },
          {
            "kind": 1,
            "oidcConfig": {
              "clientId": {
                "kind": 0,
                "environmentVariableDefaultValue": "",
                "environmentVariableName": "",
                "placeholderVariableName": "",
                "staticVariableContent": "xxx.apps.googleusercontent.com"
              },
              "clientSecret": {
                "kind": 0,
                "environmentVariableDefaultValue": "",
                "environmentVariableName": "",
                "placeholderVariableName": "",
                "staticVariableContent": "xxx"
              },
              "issuer": {
                "kind": 0,
                "environmentVariableDefaultValue": "",
                "environmentVariableName": "",
                "placeholderVariableName": "",
                "staticVariableContent": "https://accounts.google.com"
              }
            },
            "id": "google"
          }
        ],
        "authorizedRedirectUris": [
          {
            "kind": 0,
            "environmentVariableDefaultValue": "",
            "environmentVariableName": "",
            "placeholderVariableName": "",
            "staticVariableContent": "http://localhost:3000"
          }
        ],
        "authorizedRedirectUriRegexes": []
      },
      "hooks": {
        "postAuthentication": false,
        "mutatingPostAuthentication": false,
        "revalidateAuthentication": false
      },
      "jwksBased": {
        "providers": []
      }
    },
    "allowedHostNames": []
  },
  "dangerouslyEnableGraphQLEndpoint": true
}